LogisticRegression/Accuracy.py
LogisticRegression/Cost.py
LogisticRegression/Optimize.py
LogisticRegression/Predict.py
LogisticRegression/Sigmoid.py
LogisticRegression/__init__.py
LogisiticRegression_PavanAdapa-1.0.1.dist-info/LICENSE
LogisiticRegression_PavanAdapa-1.0.1.dist-info/METADATA
LogisiticRegression_PavanAdapa-1.0.1.dist-info/WHEEL
LogisiticRegression_PavanAdapa-1.0.1.dist-info/top_level.txt
LogisiticRegression_PavanAdapa-1.0.1.dist-info/RECORD
