Metadata-Version: 2.1
Name: LogisiticRegression-PavanAdapa
Version: 1.0.1
Summary: Package containing functions for logistic Regression
Home-page: https://github.com/pavanadapa/LogisiticRegression
Author: Pavan Kumar Adapa
Author-email: Pavan.adapa@uconn.edu
License: UNKNOWN
Project-URL: Git, https://github.com/pavanadapa/LogisiticRegression
Platform: UNKNOWN
Classifier: Programming Language :: Python :: 3
Classifier: License :: OSI Approved :: MIT License
Classifier: Operating System :: OS Independent
Requires-Python: >=3.6
License-File: LICENSE
